LICENSE
README.md
setup.cfg
setup.py
heartbeat/__init__.py
heartbeat/heartbeat.py
theheartbeat.egg-info/PKG-INFO
theheartbeat.egg-info/SOURCES.txt
theheartbeat.egg-info/dependency_links.txt
theheartbeat.egg-info/requires.txt
theheartbeat.egg-info/top_level.txt