Metadata-Version: 2.1
Name: theheartbeat
Version: 0.1.2
Summary: A Python module for uploading files and folders to Amazon S3 using preSigned URL.
Author: Shubham Kumar
Author-email: shubham@ioanyt.com
Classifier: Operating System :: POSIX :: Linux
Classifier: Programming Language :: Python :: 2
Classifier: Programming Language :: Python :: 2.7
Classifier: Programming Language :: Python :: 3
Classifier: Programming Language :: Python :: 3.8
Classifier: Programming Language :: Python :: 3.9
License-File: LICENSE
